api_model/__init__.py
api_model/nlextract.py
api_model/nlsuper.py
api_model/nlvisualization.py
api_model/utils/colorize.py
api_model/utils/functions.py
api_model/utils/logger.py
model_fkeywords-0.1.4.dist-info/LICENSE
model_fkeywords-0.1.4.dist-info/METADATA
model_fkeywords-0.1.4.dist-info/WHEEL
model_fkeywords-0.1.4.dist-info/dependency_links.txt
model_fkeywords-0.1.4.dist-info/top_level.txt
model_fkeywords-0.1.4.dist-info/RECORD
