Metadata-Version: 2.1
Name: model-fkeywords
Version: 0.1.4
Summary: A Natural Language Processing Library
Home-page: https://github.com/EneasJr-Rodrigues/model_fkeywords
Author: Eneas Rodrigues
Author-email: eneas.rodrigues25@gmail.com
License: Apache License
Requires-Dist: importlib-metadata
Requires-Dist: openpyxl (>=3.0.9)
Requires-Dist: pyspark (==3.1.2)
Requires-Dist: PyYAML (==5.1)
Requires-Dist: django-rss-plugin (==0.0.9)
Requires-Dist: seaborn (==0.11.1)
Requires-Dist: nltk (==3.6.5)
Requires-Dist: spacy (==3.0.3)
Requires-Dist: pendulum (==2.0.5)
Requires-Dist: requests (==2.26.0)
Requires-Dist: pygments (>=2.7.4)
Requires-Dist: gensim (>=4.0.0)
Requires-Dist: pytest
Requires-Dist: wordcloud (>=1.8.1)
Requires-Dist: kneebow
Requires-Dist: regex
Requires-Dist: cython
Requires-Dist: twine
